niwrap_c3d/c3d/__init__.py
niwrap_c3d/c3d/c2d.py
niwrap_c3d/c3d/c3d.py
niwrap_c3d/c3d/c3d_affine_tool.py
niwrap_c3d/c3d/c4d.py
niwrap_c3d-0.8.3.dist-info/WHEEL
niwrap_c3d-0.8.3.dist-info/METADATA
niwrap_c3d-0.8.3.dist-info/RECORD
